seqdataloader/attrib_config.py
seqdataloader/bounded_process_pool_executor.py
seqdataloader/queue_config.py
seqdataloader/tdb_config.py
seqdataloader/utils.py
seqdataloader/__pycache__/attrib_config.cpython-37.pyc
seqdataloader/__pycache__/bounded_process_pool_executor.cpython-37.pyc
seqdataloader/__pycache__/queue_config.cpython-37.pyc
seqdataloader/__pycache__/tdb_config.cpython-37.pyc
seqdataloader/__pycache__/utils.cpython-37.pyc
seqdataloader/batchproducers/__init__.py
seqdataloader/batchproducers/__pycache__/__init__.cpython-37.pyc
seqdataloader/batchproducers/coordbased/__init__.py
seqdataloader/batchproducers/coordbased/coordbatchproducers.py
seqdataloader/batchproducers/coordbased/coordbatchtransformers.py
seqdataloader/batchproducers/coordbased/core.py
seqdataloader/batchproducers/coordbased/__pycache__/__init__.cpython-37.pyc
seqdataloader/batchproducers/coordbased/__pycache__/coordbatchproducers.cpython-37.pyc
seqdataloader/batchproducers/coordbased/__pycache__/coordbatchtransformers.cpython-37.pyc
seqdataloader/batchproducers/coordbased/__pycache__/core.cpython-37.pyc
seqdataloader/batchproducers/coordbased/coordstovals/__init__.py
seqdataloader/batchproducers/coordbased/coordstovals/bigwig.py
seqdataloader/batchproducers/coordbased/coordstovals/core.py
seqdataloader/batchproducers/coordbased/coordstovals/fasta.py
seqdataloader/batchproducers/coordbased/coordstovals/lookup.py
seqdataloader/batchproducers/coordbased/coordstovals/test_tiledb_coords_to_vals.py
seqdataloader/batchproducers/coordbased/coordstovals/test_tiledb_coords_to_vals.py~
seqdataloader/batchproducers/coordbased/coordstovals/tiledb.py
seqdataloader/batchproducers/coordbased/coordstovals/tiledb.py~
seqdataloader/batchproducers/coordbased/coordstovals/__pycache__/__init__.cpython-37.pyc
seqdataloader/batchproducers/coordbased/coordstovals/__pycache__/bigwig.cpython-37.pyc
seqdataloader/batchproducers/coordbased/coordstovals/__pycache__/core.cpython-37.pyc
seqdataloader-1.2.dist-info/LICENSE
seqdataloader-1.2.dist-info/METADATA
seqdataloader-1.2.dist-info/WHEEL
seqdataloader-1.2.dist-info/entry_points.txt
seqdataloader-1.2.dist-info/top_level.txt
seqdataloader-1.2.dist-info/RECORD
